client_pack/__init__.py
client_pack/client/__init__.py
client_pack/client/client.py
client_pack/client/client_repository.py
client_pack/common/__init__.py
client_pack/common/messages.py
client_pack/common/utils.py
client_pack/pyqt_ui/__init__.py
client_pack/pyqt_ui/admin_page.py
client_pack/pyqt_ui/main.py
messenger_client_theksanacodes-0.0.1.dist-info/METADATA
messenger_client_theksanacodes-0.0.1.dist-info/WHEEL
messenger_client_theksanacodes-0.0.1.dist-info/top_level.txt
messenger_client_theksanacodes-0.0.1.dist-info/RECORD
